aind_s3_cache/__init__.py
aind_s3_cache/json_utils.py
aind_s3_cache/py.typed
aind_s3_cache/s3_cache.py
aind_s3_cache/uri_utils.py
aind_s3_cache/scripts/__init__.py
aind_s3_cache-0.1.0.dist-info/licenses/LICENSE
aind_s3_cache-0.1.0.dist-info/METADATA
aind_s3_cache-0.1.0.dist-info/WHEEL
aind_s3_cache-0.1.0.dist-info/top_level.txt
aind_s3_cache-0.1.0.dist-info/RECORD
