Metadata-Version: 2.4
Name: aind-s3-cache
Version: 0.1.0
Summary: Small library providing a transparent local cache for S3 objects.
Author: Allen Institute for Neural Dynamics
Author-email: Galen Lynch <galen@galenlynch.com>
License-Expression: MIT
Project-URL: Repository, https://github.com/AllenNeuralDynamics/aind-s3-cache/
Project-URL: Issues, https://github.com/AllenNeuralDynamics/aind-s3-cache/issues
Project-URL: Changelog, https://github.com/AllenNeuralDynamics/aind-s3-cache/blob/main/CHANGELOG.md
Classifier: Programming Language :: Python :: 3
Requires-Python: >=3.10
License-File: LICENSE
Requires-Dist: boto3<2,>=1
Requires-Dist: requests<3,>=2
Requires-Dist: typing-extensions>=4.7; python_version < "3.11"
Dynamic: license-file
